{
  "id" : "https://wmichelle22.github.io/Threeheads/manifests/collection.json",
  "label" : {
    "en" : [ "All manifests loaded in wmichelle22/Threeheads project" ]
  },
  "type" : "Collection",
  "@context" : "http://iiif.io/api/presentation/3/context.json",
  "items" : [ {
    "@type" : "sc:Manifest",
    "@id" : "https://wmichelle22.github.io/Threeheads/manifests/manifest2.json",
    "label" : "Three Heads Fragment of a Wall Painting"
  }, {
    "@type" : "sc:Manifest",
    "@id" : "https://wmichelle22.github.io/Threeheads/manifests/manifest.json",
    "label" : "muralfragment"
  }, {
    "@type" : "sc:Manifest",
    "@id" : "https://wmichelle22.github.io/Threeheads/manifests/muralfragment",
    "label" : "muralfragment"
  } ]
}